XxPipPackage/__init__.py
XxPipPackage/utils.py
XxPipPackage-0.0.1.dist-info/METADATA
XxPipPackage-0.0.1.dist-info/WHEEL
XxPipPackage-0.0.1.dist-info/top_level.txt
XxPipPackage-0.0.1.dist-info/RECORD
